sblpy/__init__.py
sblpy/async_connection.py
sblpy/connection.py
sblpy/query.py
sblpy/sql_adapter.py
sblpy/cli/__init__.py
sblpy/cli/entrypoint.py
sblpy/data/__init__.py
sblpy/data/cbor.py
sblpy/data/models.py
sblpy/data/types/__init__.py
sblpy/data/types/constants.py
sblpy/data/types/datetime.py
sblpy/data/types/duration.py
sblpy/data/types/future.py
sblpy/data/types/geometry.py
sblpy/data/types/range.py
sblpy/data/types/record_id.py
sblpy/data/types/table.py
sblpy/migrations/__init__.py
sblpy/migrations/db_processes.py
sblpy/migrations/file_processes.py
sblpy/migrations/migrations.py
sblpy/migrations/runner.py
sblpy/pool/__init__.py
sblpy/pool/connection_pool.py
sblpy/pool/setup_config.py
sdblpy-0.4.0.dist-info/METADATA
sdblpy-0.4.0.dist-info/WHEEL
sdblpy-0.4.0.dist-info/entry_points.txt
sdblpy-0.4.0.dist-info/top_level.txt
sdblpy-0.4.0.dist-info/RECORD
