Metadata-Version: 2.2
Name: sdblpy
Version: 0.4.0
Summary: lite surrealDB client that only supports websocket raw queries and async pooled connections
Author-email: Maxwell Flitton <maxwellflitton@gmail.com>
License: MIT License
Project-URL: Homepage, https://github.com/maxwellflitton/surreal-lite-py
Keywords: surrealdb,lite,SurrealDB,surrealDB,Surrealdb
Classifier: Programming Language :: Python :: 3
Classifier: Operating System :: OS Independent
Requires-Dist: websockets==14.2
Requires-Dist: cbor2==5.6.5
Requires-Dist: pytz==2024.2
